nessie/__init__.py
nessie/calibration.py
nessie/config.py
nessie/dataloader.py
nessie/helper.py
nessie/metrics.py
nessie/noise.py
nessie/types.py
nessie/util.py
nessie/detectors/__init__.py
nessie/detectors/baselines.py
nessie/detectors/borda_count.py
nessie/detectors/classification_entropy.py
nessie/detectors/classification_uncertainty.py
nessie/detectors/confident_learning.py
nessie/detectors/curriculum_spotter.py
nessie/detectors/datamap_confidence.py
nessie/detectors/dropout_uncertainty.py
nessie/detectors/ensemble.py
nessie/detectors/error_detector.py
nessie/detectors/irt.py
nessie/detectors/knn_entropy.py
nessie/detectors/label_aggregation.py
nessie/detectors/label_entropy.py
nessie/detectors/leitner_spotter.py
nessie/detectors/mean_distance.py
nessie/detectors/prediction_margin.py
nessie/detectors/projection_ensemble.py
nessie/detectors/retag.py
nessie/detectors/variational_principle.py
nessie/detectors/weighted_discrepancy.py
nessie/models/__init__.py
nessie/models/featurizer.py
nessie/models/model.py
nessie/models/tagging/__init__.py
nessie/models/tagging/dummy_sequence_classifier.py
nessie/models/tagging/flair_sequence_tagger.py
nessie/models/tagging/handcrafted_crf_sequence_tagger.py
nessie/models/tagging/maxent_sequence_tagger.py
nessie/models/tagging/transformer_sequence_tagger.py
nessie/models/tagging/util.py
nessie/models/text/__init__.py
nessie/models/text/dummy_text_classifier.py
nessie/models/text/fasttext_text_classifier.py
nessie/models/text/flair_text_classifier.py
nessie/models/text/lightgbm_text_classifier.py
nessie/models/text/maxent_text_classifier.py
nessie/models/text/sklean_text_classifier.py
nessie/models/text/transformer_text_classifier.py
nessie/task_support/__init__.py
nessie/task_support/span_labeling.py
nessie-0.1.1.dist-info/LICENSE
nessie-0.1.1.dist-info/WHEEL
nessie-0.1.1.dist-info/METADATA
nessie-0.1.1.dist-info/RECORD
