Metadata-Version: 2.1
Name: nessie
Version: 0.1.1
Summary: Annotation error detection and correction
Author-email: Jan-Christoph Klie <git@mrklie.com>
Requires-Python: >=3.8
Classifier: Intended Audience :: Developers
Classifier: License :: OSI Approved :: MIT License
Classifier: Programming Language :: Python :: 3
Classifier: Topic :: Software Development :: Libraries :: Python Modules
Requires-Dist: torch>=1.11.0
Requires-Dist: flair==0.11.*
Requires-Dist: sacremoses>=0.0.53
Requires-Dist: slurmee
Requires-Dist: transformers>=4.16.1
Requires-Dist: numpy>=1.22.1
Requires-Dist: scipy>=1.7.3
Requires-Dist: backoff>=1.11.1
Requires-Dist: datasets>=1.18.2
Requires-Dist: pandas>=1.4.0
Requires-Dist: wget>=3.2
Requires-Dist: pyro-ppl>=1.8.0
Requires-Dist: cleanlab>=1.0
Requires-Dist: lightgbm>=3.3.2
Requires-Dist: diskcache>=5.4.0
Requires-Dist: fasttext>=0.9.2
Requires-Dist: cleantext>=1.1.4
Requires-Dist: sentence-transformers>=2.1.0
Requires-Dist: sklearn-crfsuite>=0.3.6
Requires-Dist: seqeval>=1.2.2
Requires-Dist: faiss-cpu>=1.7.2
Requires-Dist: crowd-kit>=0.0.9
Requires-Dist: iobes>=1.5.1
Requires-Dist: suffix-tree>=0.0.7
Requires-Dist: awkward>=1.7.0
Requires-Dist: netcal>=1.2.1
Requires-Dist: pooch>=1.6.0
Requires-Dist: ireval>=0.1.1
Requires-Dist: jupyter>=1.0.0
Requires-Dist: pytest>=6.2 ; extra == "dev"
Requires-Dist: black>=22.1.0 ; extra == "dev"
Requires-Dist: isort>=5.10.1 ; extra == "dev"
Requires-Dist: seaborn>=0.11.2 ; extra == "doc"
Requires-Dist: notebook>=6.4.8 ; extra == "doc"
Requires-Dist: Sphinx>=4.4.0 ; extra == "doc"
Requires-Dist: m2r2>=0.3.2 ; extra == "doc"
Requires-Dist: sphinx-autodoc-typehints>=1.17.0 ; extra == "doc"
Requires-Dist: sphinx-rtd-theme>=1.0.0 ; extra == "doc"
Requires-Dist: sphinx-autoapi>=1.8.4 ; extra == "doc"
Requires-Dist: nbsphinx>=0.8.8 ; extra == "doc"
Requires-Dist: sphinx-copybutton>=0.5.0 ; extra == "doc"
Requires-Dist: nbsphinx-link>=1.3.0 ; extra == "doc"
Requires-Dist: nbstripout>=0.5.0 ; extra == "doc"
Requires-Dist: pre-commit>=2.17.0 ; extra == "doc"
Requires-Dist: sphinx_rst_builder ; extra == "doc"
Project-URL: Home, https://github.com/jcklie/nessie/
Provides-Extra: dev
Provides-Extra: doc
